Mp4ToGif/__init__.py
Mp4ToGif-0.0.1.dist-info/LICENSE.txt
Mp4ToGif-0.0.1.dist-info/METADATA
Mp4ToGif-0.0.1.dist-info/WHEEL
Mp4ToGif-0.0.1.dist-info/top_level.txt
Mp4ToGif-0.0.1.dist-info/RECORD
