Metadata-Version: 2.1
Name: Mp4ToGif
Version: 0.0.1
Summary: A small package that makes gifes outof mp4 clips
Home-page: https://github.com/MasterErlend/Mp4ToGif
Author: MasterErlend
License: UNKNOWN
Platform: UNKNOWN
Classifier: Programming Language :: Python :: 3
Classifier: License :: OSI Approved :: MIT License
Classifier: Operating System :: OS Independent
